rfc3161_client-1.0.4.dist-info/METADATA
rfc3161_client-1.0.4.dist-info/WHEEL
rfc3161_client-1.0.4.dist-info/licenses/LICENSE
rfc3161_client/__init__.py
rfc3161_client/_rust.pyd
rfc3161_client/_rust/__init__.pyi
rfc3161_client/_rust/verify/__init__.pyi
rfc3161_client/base.py
rfc3161_client/errors.py
rfc3161_client/py.typed
rfc3161_client/tsp.py
rfc3161_client/verify.py
rfc3161_client-1.0.4.dist-info/RECORD
